uart_rx.v
module uart_rx #(
    parameter RX_CLK_LIMIT = 27 // 50,000,000 / 115,200 x 16
)(input clk, input rst_n, input rx_serial, output reg [7:0] rx_data, output reg rx_ready);//a 1-cycle pulse when a byte is fully collected

        wire sample_tick;
        reg [5:0] clk_count;

        localparam STATE_IDLE  = 2'b00;
        localparam STATE_START = 2'b01;
        localparam STATE_DATA  = 2'b10;
        localparam STATE_STOP  = 2'b11;

        always @(posedge clk) begin
        if (!rst_n) begin
        clk_count <= 0;
        end else begin
            if (clk_count == RX_CLK_LIMIT - 1) begin
                clk_count <= 0;
            end else begin
                clk_count <= clk_count + 1;
            end
        end
    end 

    assign sample_tick = (clk_count == RX_CLK_LIMIT - 1); //sample_tick is high when clk_count == 26, this is 16 times faster than baude rate

    //fsm
    reg [1:0] current_state; //fsm states
    reg [3:0] tick_count;   //count the 16 oversampling ticks per bit
    reg [2:0] bit_index;    //track which data bit you are receiving
    reg [7:0] rx_data_reg;  //accumulate the bits as they arrive

    always @(posedge clk) begin
        if (!rst_n) begin
            current_state <= STATE_IDLE;
            tick_count <= 0;
            bit_index <= 0;
            rx_ready <= 0;
            rx_data <= 0;
        end
        else begin
            rx_ready <= 1'b0; //ensures that if it becomes 1 in STATE_STOP, it automatically drops back down to 0 on the very next clock cycle, giving us a perfect 1-cycle pulse.
            case(current_state) 
                STATE_IDLE: if (!rx_serial) begin
                    tick_count <= 0;
                    current_state <= STATE_START;
                end
                STATE_START: if(sample_tick) begin 
                    if(tick_count < 7) tick_count <= tick_count + 1;
                    else begin
                        if (!rx_serial) begin
                            tick_count <= 0;
                            bit_index <= 0;
                            current_state <= STATE_DATA;
                        end
                        else current_state <= STATE_IDLE;
                end
        end
                STATE_DATA: 
                if(sample_tick) begin
                    if(tick_count < 15) tick_count <= tick_count + 1;
                    else if(tick_count == 15) begin
                    rx_data_reg[bit_index] <= rx_serial;
                    tick_count <= 0;
                
                if (bit_index == 7) current_state <= STATE_STOP;
                else bit_index <= bit_index + 1;
                end
                end

                STATE_STOP:
                if(sample_tick) begin
                    if(tick_count < 15) tick_count <= tick_count + 1;
                    else begin
                        if (rx_serial) begin
                            rx_data <= rx_data_reg;
                            rx_ready <= 1'b1;
                            current_state <= STATE_IDLE;
                        end
                        else current_state <= STATE_IDLE;
                    end
                end

        endcase
        end
    end
    
endmodule

uart_tx.v
module uart_tx #(
    parameter TX_CLK_LIMIT = 434 // 50,000,000 / 115,200
)(input clk, input rst_n, input tx_start, input [7:0] tx_data, output bit_tick, output reg tx_serial, output tx_busy);
    reg [15:0] clk_count;
    reg [1:0] current_state;
    reg [2:0] bit_index;   // i need this to count from bit 0 to bit 7 during transmission
    reg [7:0] tx_data_reg; // A safe holding register to store the data while i transmit it hit by bit

    localparam STATE_IDLE  = 2'b00;
    localparam STATE_START = 2'b01;
    localparam STATE_DATA  = 2'b10;
    localparam STATE_STOP  = 2'b11;

    // for baud rate generation
    always @(posedge clk) begin
        if (!rst_n) begin
        clk_count <= 0;
        end else if (current_state == STATE_IDLE && tx_start) begin
        clk_count <= 0; // Force-reset the metronome when a new packet begins
        end else begin
            if (clk_count == TX_CLK_LIMIT - 1) begin
                clk_count <= 0;
            end else begin
                clk_count <= clk_count + 1;
            end
        end
    end 
        assign bit_tick = (clk_count == TX_CLK_LIMIT - 1);
    
    //fsm 
    always @(posedge clk) begin
        if (!rst_n) begin
            current_state <= STATE_IDLE;
            tx_serial     <= 1'b1;
            bit_index     <= 0;
            tx_data_reg   <= 0;
        end else begin
            case (current_state)
                STATE_IDLE: begin
                    tx_serial <= 1'b1; // Idle line is always high
                    if (tx_start) begin
                        tx_data_reg   <= tx_data;
                        bit_index     <= 0;
                        current_state <= STATE_START;
                    end
                end

                STATE_START: begin
                    tx_serial <= 1'b0; // Start bit is always low
                    if (bit_tick) begin
                        current_state <= STATE_DATA;
                    end
                end

                STATE_DATA: begin
                    tx_serial <= tx_data_reg[bit_index];// 1. Set tx_serial to the current bit of tx_data_reg using bit_index
                    if (bit_tick) begin
                            if (bit_index == 7) current_state <= STATE_STOP;
                            else bit_index <= bit_index + 1;
                    end // 2. If a bit_tick happens, check if we hit index 7 to move to STATE_STOP, 
                    //    otherwise increment bit_index.
                end

                STATE_STOP: begin
                    tx_serial <= 1'b1; // 1. Set tx_serial back to 1'b1
                    if (bit_tick) current_state <= STATE_IDLE; // 2. If a bit_tick happens, go back to STATE_IDLE
                end
                
                default: current_state <= STATE_IDLE;
            endcase
        end
    end

    assign tx_busy = ((current_state == STATE_START)||(current_state == STATE_DATA)||(current_state == STATE_STOP));

endmodule

uart_tb.v
`timescale 1ns / 1ps

module uart_tb;
parameter CLK_PERIOD = 20;
parameter FAST_TX_LIMIT = 16; // Scaled down for fast simulation
parameter FAST_RX_LIMIT = 1;  // Scaled down (approx 10/16 ~ 1)

//system signals
reg clk;
reg rst_n;

// Signal Declarations
reg        tx_start; //Control signal pulsed HIGH by testbench to trigger sending a byte.
reg  [7:0] tx_data; //8-bit register holding the byte value to transmit.
wire       bit_tick; //Output net from transmitter indicating each bit duration boundary.
wire       tx_busy; //Output flag from transmitter: 1 when transmitting, 0 when idle.
wire       tx_serial; //A 1-bit net (wire) that carries the serial data stream bit-by-bit.

wire [7:0] rx_data; //An 8-bit bus holding the fully reconstructed byte received over serial.
wire       rx_ready; //A 1-bit flag pulsed HIGH for one clock cycle when a byte is completely received.

// 2. Module Instantiations (DUT)
uart_tx #(
        .TX_CLK_LIMIT(FAST_TX_LIMIT)
    ) u_uart_tx (
        .clk       (clk),
        .rst_n     (rst_n),
        .tx_start  (tx_start),
        .tx_data   (tx_data),
        .bit_tick  (bit_tick),
        .tx_serial (tx_serial),
        .tx_busy   (tx_busy)
    );

// Instantiate UART Receiver (Loopback: rx_serial connected to tx_serial)
    uart_rx #(
        .RX_CLK_LIMIT(FAST_RX_LIMIT)
    ) u_uart_rx (
        .clk       (clk),
        .rst_n     (rst_n),
        .rx_serial (tx_serial), // Directly wired to TX serial output!
        .rx_data   (rx_data),
        .rx_ready  (rx_ready)
    );

// Clock Generation
    initial begin
        clk = 1'b0;
        forever #(CLK_PERIOD / 2) clk = ~clk;
    end

// VCD Waveform Recording
    initial begin
        $dumpfile("uart_sim.vcd");
        $dumpvars(0, uart_tb);
    end

//Verification Task
task send_and_check(input [7:0] test_byte);
        begin
            @(posedge clk);
            
            if (tx_busy) begin
                $display("[%0t ns] [WAIT] Waiting for TX to become idle...", $time);
                wait (!tx_busy);
                @(posedge clk);
            end

            tx_data  <= test_byte;
            tx_start <= 1'b1;
            @(posedge clk);
            tx_start <= 1'b0;

            $display("[%0t ns] [TX] Started sending byte: 0x%0h (8'b%0b)", $time, test_byte, test_byte);

            @(posedge rx_ready);
            
            if (rx_data === test_byte) begin
                $display("[%0t ns] [PASS] Successfully received matching byte: 0x%0h\n", $time, rx_data);
            end else begin
                $display("[%0t ns] [FAIL] ERROR! Sent: 0x%0h | Received: 0x%0h\n", $time, test_byte, rx_data);
            end
        end
    endtask


    //Test Sequence Execution
    initial begin
        rst_n    = 1'b0;
        tx_start = 1'b0;
        tx_data  = 8'h00;

        #(CLK_PERIOD * 5);
        rst_n = 1'b1;
        #(CLK_PERIOD * 5);

        $display("\n==================================================");
        $display("       STARTING UART LOOPBACK VERIFICATION        ");
        $display("==================================================\n");

        send_and_check(8'hA5);
        send_and_check(8'h5A);
        send_and_check(8'h55);
        send_and_check(8'hFF);

        $display("==================================================");
        $display("          ALL TESTS COMPLETED SUCCESSFULLY        ");
        $display("==================================================\n");

        $finish;
    end


endmodule

uart_sim.vcd
$date
	Sun Jul 26 11:10:08 2026
$end
$version
	Icarus Verilog
$end
$timescale
	1ps
$end
$scope module uart_tb $end
$var wire 1 ! tx_serial $end
$var wire 1 " tx_busy $end
$var wire 1 # rx_ready $end
$var wire 8 $ rx_data [7:0] $end
$var wire 1 % bit_tick $end
$var parameter 32 & CLK_PERIOD $end
$var parameter 32 ' FAST_RX_LIMIT $end
$var parameter 32 ( FAST_TX_LIMIT $end
$var reg 1 ) clk $end
$var reg 1 * rst_n $end
$var reg 8 + tx_data [7:0] $end
$var reg 1 , tx_start $end
$scope module u_uart_rx $end
$var wire 1 ) clk $end
$var wire 1 * rst_n $end
$var wire 1 - sample_tick $end
$var wire 1 ! rx_serial $end
$var parameter 32 . RX_CLK_LIMIT $end
$var parameter 2 / STATE_DATA $end
$var parameter 2 0 STATE_IDLE $end
$var parameter 2 1 STATE_START $end
$var parameter 2 2 STATE_STOP $end
$var reg 3 3 bit_index [2:0] $end
$var reg 6 4 clk_count [5:0] $end
$var reg 2 5 current_state [1:0] $end
$var reg 8 6 rx_data [7:0] $end
$var reg 8 7 rx_data_reg [7:0] $end
$var reg 1 # rx_ready $end
$var reg 4 8 tick_count [3:0] $end
$upscope $end
$scope module u_uart_tx $end
$var wire 1 ) clk $end
$var wire 1 * rst_n $end
$var wire 1 " tx_busy $end
$var wire 8 9 tx_data [7:0] $end
$var wire 1 , tx_start $end
$var wire 1 % bit_tick $end
$var parameter 2 : STATE_DATA $end
$var parameter 2 ; STATE_IDLE $end
$var parameter 2 < STATE_START $end
$var parameter 2 = STATE_STOP $end
$var parameter 32 > TX_CLK_LIMIT $end
$var reg 3 ? bit_index [2:0] $end
$var reg 16 @ clk_count [15:0] $end
$var reg 2 A current_state [1:0] $end
$var reg 8 B tx_data_reg [7:0] $end
$var reg 1 ! tx_serial $end
$upscope $end
$scope task send_and_check $end
$var reg 8 C test_byte [7:0] $end
$upscope $end
$upscope $end
$enddefinitions $end
$comment Show the parameter values. $end
$dumpall
b10000 >
b11 =
b1 <
b0 ;
b10 :
b11 2
b1 1
b0 0
b10 /
b1 .
b10000 (
b1 '
b10100 &
$end
#0
$dumpvars
bx C
bx B
bx A
bx @
bx ?
b0 9
bx 8
bx 7
bx 6
bx 5
bx 4
bx 3
x-
0,
b0 +
0*
0)
x%
bx $
x#
x"
x!
$end
#10000
0"
0%
1-
b0 @
b0 B
b0 ?
1!
b0 A
b0 4
b0 $
b0 6
0#
b0 3
b0 8
b0 5
1)
#20000
0)
#30000
1)
#40000
0)
#50000
1)
#60000
0)
#70000
1)
#80000
0)
#90000
1)
#100000
0)
1*
#110000
b1 @
1)
#120000
0)
#130000
b10 @
1)
#140000
0)
#150000
b11 @
1)
#160000
0)
#170000
b100 @
1)
#180000
0)
#190000
b101 @
1)
#200000
0)
b10100101 C
#210000
b110 @
1,
b10100101 +
b10100101 9
1)
#220000
0)
#230000
1"
0,
b1 A
b10100101 B
b0 @
1)
#240000
0)
#250000
b1 @
0!
1)
#260000
0)
#270000
b1 5
b10 @
1)
#280000
0)
#290000
b11 @
b1 8
1)
#300000
0)
#310000
b10 8
b100 @
1)
#320000
0)
#330000
b101 @
b11 8
1)
#340000
0)
#350000
b100 8
b110 @
1)
#360000
0)
#370000
b111 @
b101 8
1)
#380000
0)
#390000
b110 8
b1000 @
1)
#400000
0)
#410000
b1001 @
b111 8
1)
#420000
0)
#430000
b10 5
b0 8
b1010 @
1)
#440000
0)
#450000
b1011 @
b1 8
1)
#460000
0)
#470000
b10 8
b1100 @
1)
#480000
0)
#490000
b1101 @
b11 8
1)
#500000
0)
#510000
b100 8
b1110 @
1)
#520000
0)
#530000
1%
b1111 @
b101 8
1)
#540000
0)
#550000
0%
b110 8
b10 A
b0 @
1)
#560000
0)
#570000
b1 @
1!
b111 8
1)
#580000
0)
#590000
b1000 8
b10 @
1)
#600000
0)
#610000
b11 @
b1001 8
1)
#620000
0)
#630000
b1010 8
b100 @
1)
#640000
0)
#650000
b101 @
b1011 8
1)
#660000
0)
#670000
b1100 8
b110 @
1)
#680000
0)
#690000
b111 @
b1101 8
1)
#700000
0)
#710000
b1110 8
b1000 @
1)
#720000
0)
#730000
b1001 @
b1111 8
1)
#740000
0)
#750000
b1 3
b0 8
bx1 7
b1010 @
1)
#760000
0)
#770000
b1011 @
b1 8
1)
#780000
0)
#790000
b10 8
b1100 @
1)
#800000
0)
#810000
b1101 @
b11 8
1)
#820000
0)
#830000
b100 8
b1110 @
1)
#840000
0)
#850000
1%
b1111 @
b101 8
1)
#860000
0)
#870000
0%
b110 8
b1 ?
b0 @
1)
#880000
0)
#890000
b1 @
0!
b111 8
1)
#900000
0)
#910000
b1000 8
b10 @
1)
#920000
0)
#930000
b11 @
b1001 8
1)
#940000
0)
#950000
b1010 8
b100 @
1)
#960000
0)
#970000
b101 @
b1011 8
1)
#980000
0)
#990000
b1100 8
b110 @
1)
#1000000
0)
#1010000
b111 @
b1101 8
1)
#1020000
0)
#1030000
b1110 8
b1000 @
1)
#1040000
0)
#1050000
b1001 @
b1111 8
1)
#1060000
0)
#1070000
b10 3
b0 8
bx01 7
b1010 @
1)
#1080000
0)
#1090000
b1011 @
b1 8
1)
#1100000
0)
#1110000
b10 8
b1100 @
1)
#1120000
0)
#1130000
b1101 @
b11 8
1)
#1140000
0)
#1150000
b100 8
b1110 @
1)
#1160000
0)
#1170000
1%
b1111 @
b101 8
1)
#1180000
0)
#1190000
0%
b110 8
b10 ?
b0 @
1)
#1200000
0)
#1210000
b1 @
1!
b111 8
1)
#1220000
0)
#1230000
b1000 8
b10 @
1)
#1240000
0)
#1250000
b11 @
b1001 8
1)
#1260000
0)
#1270000
b1010 8
b100 @
1)
#1280000
0)
#1290000
b101 @
b1011 8
1)
#1300000
0)
#1310000
b1100 8
b110 @
1)
#1320000
0)
#1330000
b111 @
b1101 8
1)
#1340000
0)
#1350000
b1110 8
b1000 @
1)
#1360000
0)
#1370000
b1001 @
b1111 8
1)
#1380000
0)
#1390000
b11 3
b0 8
bx101 7
b1010 @
1)
#1400000
0)
#1410000
b1011 @
b1 8
1)
#1420000
0)
#1430000
b10 8
b1100 @
1)
#1440000
0)
#1450000
b1101 @
b11 8
1)
#1460000
0)
#1470000
b100 8
b1110 @
1)
#1480000
0)
#1490000
1%
b1111 @
b101 8
1)
#1500000
0)
#1510000
0%
b110 8
b11 ?
b0 @
1)
#1520000
0)
#1530000
b1 @
0!
b111 8
1)
#1540000
0)
#1550000
b1000 8
b10 @
1)
#1560000
0)
#1570000
b11 @
b1001 8
1)
#1580000
0)
#1590000
b1010 8
b100 @
1)
#1600000
0)
#1610000
b101 @
b1011 8
1)
#1620000
0)
#1630000
b1100 8
b110 @
1)
#1640000
0)
#1650000
b111 @
b1101 8
1)
#1660000
0)
#1670000
b1110 8
b1000 @
1)
#1680000
0)
#1690000
b1001 @
b1111 8
1)
#1700000
0)
#1710000
b100 3
b0 8
bx0101 7
b1010 @
1)
#1720000
0)
#1730000
b1011 @
b1 8
1)
#1740000
0)
#1750000
b10 8
b1100 @
1)
#1760000
0)
#1770000
b1101 @
b11 8
1)
#1780000
0)
#1790000
b100 8
b1110 @
1)
#1800000
0)
#1810000
1%
b1111 @
b101 8
1)
#1820000
0)
#1830000
0%
b110 8
b100 ?
b0 @
1)
#1840000
0)
#1850000
b1 @
b111 8
1)
#1860000
0)
#1870000
b1000 8
b10 @
1)
#1880000
0)
#1890000
b11 @
b1001 8
1)
#1900000
0)
#1910000
b1010 8
b100 @
1)
#1920000
0)
#1930000
b101 @
b1011 8
1)
#1940000
0)
#1950000
b1100 8
b110 @
1)
#1960000
0)
#1970000
b111 @
b1101 8
1)
#1980000
0)
#1990000
b1110 8
b1000 @
1)
#2000000
0)
#2010000
b1001 @
b1111 8
1)
#2020000
0)
#2030000
b101 3
b0 8
bx00101 7
b1010 @
1)
#2040000
0)
#2050000
b1011 @
b1 8
1)
#2060000
0)
#2070000
b10 8
b1100 @
1)
#2080000
0)
#2090000
b1101 @
b11 8
1)
#2100000
0)
#2110000
b100 8
b1110 @
1)
#2120000
0)
#2130000
1%
b1111 @
b101 8
1)
#2140000
0)
#2150000
0%
b110 8
b101 ?
b0 @
1)
#2160000
0)
#2170000
b1 @
1!
b111 8
1)
#2180000
0)
#2190000
b1000 8
b10 @
1)
#2200000
0)
#2210000
b11 @
b1001 8
1)
#2220000
0)
#2230000
b1010 8
b100 @
1)
#2240000
0)
#2250000
b101 @
b1011 8
1)
#2260000
0)
#2270000
b1100 8
b110 @
1)
#2280000
0)
#2290000
b111 @
b1101 8
1)
#2300000
0)
#2310000
b1110 8
b1000 @
1)
#2320000
0)
#2330000
b1001 @
b1111 8
1)
#2340000
0)
#2350000
b110 3
b0 8
bx100101 7
b1010 @
1)
#2360000
0)
#2370000
b1011 @
b1 8
1)
#2380000
0)
#2390000
b10 8
b1100 @
1)
#2400000
0)
#2410000
b1101 @
b11 8
1)
#2420000
0)
#2430000
b100 8
b1110 @
1)
#2440000
0)
#2450000
1%
b1111 @
b101 8
1)
#2460000
0)
#2470000
0%
b110 8
b110 ?
b0 @
1)
#2480000
0)
#2490000
b1 @
0!
b111 8
1)
#2500000
0)
#2510000
b1000 8
b10 @
1)
#2520000
0)
#2530000
b11 @
b1001 8
1)
#2540000
0)
#2550000
b1010 8
b100 @
1)
#2560000
0)
#2570000
b101 @
b1011 8
1)
#2580000
0)
#2590000
b1100 8
b110 @
1)
#2600000
0)
#2610000
b111 @
b1101 8
1)
#2620000
0)
#2630000
b1110 8
b1000 @
1)
#2640000
0)
#2650000
b1001 @
b1111 8
1)
#2660000
0)
#2670000
b111 3
b0 8
bx0100101 7
b1010 @
1)
#2680000
0)
#2690000
b1011 @
b1 8
1)
#2700000
0)
#2710000
b10 8
b1100 @
1)
#2720000
0)
#2730000
b1101 @
b11 8
1)
#2740000
0)
#2750000
b100 8
b1110 @
1)
#2760000
0)
#2770000
1%
b1111 @
b101 8
1)
#2780000
0)
#2790000
0%
b110 8
b111 ?
b0 @
1)
#2800000
0)
#2810000
b1 @
1!
b111 8
1)
#2820000
0)
#2830000
b1000 8
b10 @
1)
#2840000
0)
#2850000
b11 @
b1001 8
1)
#2860000
0)
#2870000
b1010 8
b100 @
1)
#2880000
0)
#2890000
b101 @
b1011 8
1)
#2900000
0)
#2910000
b1100 8
b110 @
1)
#2920000
0)
#2930000
b111 @
b1101 8
1)
#2940000
0)
#2950000
b1110 8
b1000 @
1)
#2960000
0)
#2970000
b1001 @
b1111 8
1)
#2980000
0)
#2990000
b11 5
b0 8
b10100101 7
b1010 @
1)
#3000000
0)
#3010000
b1011 @
b1 8
1)
#3020000
0)
#3030000
b10 8
b1100 @
1)
#3040000
0)
#3050000
b1101 @
b11 8
1)
#3060000
0)
#3070000
b100 8
b1110 @
1)
#3080000
0)
#3090000
1%
b1111 @
b101 8
1)
#3100000
0)
#3110000
0%
b110 8
b11 A
b0 @
1)
#3120000
0)
#3130000
b1 @
b111 8
1)
#3140000
0)
#3150000
b1000 8
b10 @
1)
#3160000
0)
#3170000
b11 @
b1001 8
1)
#3180000
0)
#3190000
b1010 8
b100 @
1)
#3200000
0)
#3210000
b101 @
b1011 8
1)
#3220000
0)
#3230000
b1100 8
b110 @
1)
#3240000
0)
#3250000
b111 @
b1101 8
1)
#3260000
0)
#3270000
b1110 8
b1000 @
1)
#3280000
0)
#3290000
b1001 @
b1111 8
1)
#3300000
0)
#3310000
b1011010 C
b0 5
1#
b10100101 $
b10100101 6
b1010 @
1)
#3320000
0)
#3330000
b1011 @
0#
1)
#3340000
0)
#3350000
b1100 @
1)
#3360000
0)
#3370000
b1101 @
1)
#3380000
0)
#3390000
b1110 @
1)
#3400000
0)
#3410000
1%
b1111 @
1)
#3420000
0)
#3430000
0"
0%
b0 A
b0 @
1)
#3440000
0)
#3450000
b1 @
1,
b1011010 +
b1011010 9
1)
#3460000
0)
#3470000
1"
0,
b1 A
b0 ?
b1011010 B
b0 @
1)
#3480000
0)
#3490000
b1 @
0!
1)
#3500000
0)
#3510000
b1 5
b0 8
b10 @
1)
#3520000
0)
#3530000
b11 @
b1 8
1)
#3540000
0)
#3550000
b10 8
b100 @
1)
#3560000
0)
#3570000
b101 @
b11 8
1)
#3580000
0)
#3590000
b100 8
b110 @
1)
#3600000
0)
#3610000
b111 @
b101 8
1)
#3620000
0)
#3630000
b110 8
b1000 @
1)
#3640000
0)
#3650000
b1001 @
b111 8
1)
#3660000
0)
#3670000
b10 5
b0 3
b0 8
b1010 @
1)
#3680000
0)
#3690000
b1011 @
b1 8
1)
#3700000
0)
#3710000
b10 8
b1100 @
1)
#3720000
0)
#3730000
b1101 @
b11 8
1)
#3740000
0)
#3750000
b100 8
b1110 @
1)
#3760000
0)
#3770000
1%
b1111 @
b101 8
1)
#3780000
0)
#3790000
0%
b110 8
b10 A
b0 @
1)
#3800000
0)
#3810000
b1 @
b111 8
1)
#3820000
0)
#3830000
b1000 8
b10 @
1)
#3840000
0)
#3850000
b11 @
b1001 8
1)
#3860000
0)
#3870000
b1010 8
b100 @
1)
#3880000
0)
#3890000
b101 @
b1011 8
1)
#3900000
0)
#3910000
b1100 8
b110 @
1)
#3920000
0)
#3930000
b111 @
b1101 8
1)
#3940000
0)
#3950000
b1110 8
b1000 @
1)
#3960000
0)
#3970000
b1001 @
b1111 8
1)
#3980000
0)
#3990000
b1 3
b0 8
b10100100 7
b1010 @
1)
#4000000
0)
#4010000
b1011 @
b1 8
1)
#4020000
0)
#4030000
b10 8
b1100 @
1)
#4040000
0)
#4050000
b1101 @
b11 8
1)
#4060000
0)
#4070000
b100 8
b1110 @
1)
#4080000
0)
#4090000
1%
b1111 @
b101 8
1)
#4100000
0)
#4110000
0%
b110 8
b1 ?
b0 @
1)
#4120000
0)
#4130000
b1 @
1!
b111 8
1)
#4140000
0)
#4150000
b1000 8
b10 @
1)
#4160000
0)
#4170000
b11 @
b1001 8
1)
#4180000
0)
#4190000
b1010 8
b100 @
1)
#4200000
0)
#4210000
b101 @
b1011 8
1)
#4220000
0)
#4230000
b1100 8
b110 @
1)
#4240000
0)
#4250000
b111 @
b1101 8
1)
#4260000
0)
#4270000
b1110 8
b1000 @
1)
#4280000
0)
#4290000
b1001 @
b1111 8
1)
#4300000
0)
#4310000
b10 3
b0 8
b10100110 7
b1010 @
1)
#4320000
0)
#4330000
b1011 @
b1 8
1)
#4340000
0)
#4350000
b10 8
b1100 @
1)
#4360000
0)
#4370000
b1101 @
b11 8
1)
#4380000
0)
#4390000
b100 8
b1110 @
1)
#4400000
0)
#4410000
1%
b1111 @
b101 8
1)
#4420000
0)
#4430000
0%
b110 8
b10 ?
b0 @
1)
#4440000
0)
#4450000
b1 @
0!
b111 8
1)
#4460000
0)
#4470000
b1000 8
b10 @
1)
#4480000
0)
#4490000
b11 @
b1001 8
1)
#4500000
0)
#4510000
b1010 8
b100 @
1)
#4520000
0)
#4530000
b101 @
b1011 8
1)
#4540000
0)
#4550000
b1100 8
b110 @
1)
#4560000
0)
#4570000
b111 @
b1101 8
1)
#4580000
0)
#4590000
b1110 8
b1000 @
1)
#4600000
0)
#4610000
b1001 @
b1111 8
1)
#4620000
0)
#4630000
b11 3
b0 8
b10100010 7
b1010 @
1)
#4640000
0)
#4650000
b1011 @
b1 8
1)
#4660000
0)
#4670000
b10 8
b1100 @
1)
#4680000
0)
#4690000
b1101 @
b11 8
1)
#4700000
0)
#4710000
b100 8
b1110 @
1)
#4720000
0)
#4730000
1%
b1111 @
b101 8
1)
#4740000
0)
#4750000
0%
b110 8
b11 ?
b0 @
1)
#4760000
0)
#4770000
b1 @
1!
b111 8
1)
#4780000
0)
#4790000
b1000 8
b10 @
1)
#4800000
0)
#4810000
b11 @
b1001 8
1)
#4820000
0)
#4830000
b1010 8
b100 @
1)
#4840000
0)
#4850000
b101 @
b1011 8
1)
#4860000
0)
#4870000
b1100 8
b110 @
1)
#4880000
0)
#4890000
b111 @
b1101 8
1)
#4900000
0)
#4910000
b1110 8
b1000 @
1)
#4920000
0)
#4930000
b1001 @
b1111 8
1)
#4940000
0)
#4950000
b100 3
b0 8
b10101010 7
b1010 @
1)
#4960000
0)
#4970000
b1011 @
b1 8
1)
#4980000
0)
#4990000
b10 8
b1100 @
1)
#5000000
0)
#5010000
b1101 @
b11 8
1)
#5020000
0)
#5030000
b100 8
b1110 @
1)
#5040000
0)
#5050000
1%
b1111 @
b101 8
1)
#5060000
0)
#5070000
0%
b110 8
b100 ?
b0 @
1)
#5080000
0)
#5090000
b1 @
b111 8
1)
#5100000
0)
#5110000
b1000 8
b10 @
1)
#5120000
0)
#5130000
b11 @
b1001 8
1)
#5140000
0)
#5150000
b1010 8
b100 @
1)
#5160000
0)
#5170000
b101 @
b1011 8
1)
#5180000
0)
#5190000
b1100 8
b110 @
1)
#5200000
0)
#5210000
b111 @
b1101 8
1)
#5220000
0)
#5230000
b1110 8
b1000 @
1)
#5240000
0)
#5250000
b1001 @
b1111 8
1)
#5260000
0)
#5270000
b101 3
b0 8
b10111010 7
b1010 @
1)
#5280000
0)
#5290000
b1011 @
b1 8
1)
#5300000
0)
#5310000
b10 8
b1100 @
1)
#5320000
0)
#5330000
b1101 @
b11 8
1)
#5340000
0)
#5350000
b100 8
b1110 @
1)
#5360000
0)
#5370000
1%
b1111 @
b101 8
1)
#5380000
0)
#5390000
0%
b110 8
b101 ?
b0 @
1)
#5400000
0)
#5410000
b1 @
0!
b111 8
1)
#5420000
0)
#5430000
b1000 8
b10 @
1)
#5440000
0)
#5450000
b11 @
b1001 8
1)
#5460000
0)
#5470000
b1010 8
b100 @
1)
#5480000
0)
#5490000
b101 @
b1011 8
1)
#5500000
0)
#5510000
b1100 8
b110 @
1)
#5520000
0)
#5530000
b111 @
b1101 8
1)
#5540000
0)
#5550000
b1110 8
b1000 @
1)
#5560000
0)
#5570000
b1001 @
b1111 8
1)
#5580000
0)
#5590000
b110 3
b0 8
b10011010 7
b1010 @
1)
#5600000
0)
#5610000
b1011 @
b1 8
1)
#5620000
0)
#5630000
b10 8
b1100 @
1)
#5640000
0)
#5650000
b1101 @
b11 8
1)
#5660000
0)
#5670000
b100 8
b1110 @
1)
#5680000
0)
#5690000
1%
b1111 @
b101 8
1)
#5700000
0)
#5710000
0%
b110 8
b110 ?
b0 @
1)
#5720000
0)
#5730000
b1 @
1!
b111 8
1)
#5740000
0)
#5750000
b1000 8
b10 @
1)
#5760000
0)
#5770000
b11 @
b1001 8
1)
#5780000
0)
#5790000
b1010 8
b100 @
1)
#5800000
0)
#5810000
b101 @
b1011 8
1)
#5820000
0)
#5830000
b1100 8
b110 @
1)
#5840000
0)
#5850000
b111 @
b1101 8
1)
#5860000
0)
#5870000
b1110 8
b1000 @
1)
#5880000
0)
#5890000
b1001 @
b1111 8
1)
#5900000
0)
#5910000
b111 3
b0 8
b11011010 7
b1010 @
1)
#5920000
0)
#5930000
b1011 @
b1 8
1)
#5940000
0)
#5950000
b10 8
b1100 @
1)
#5960000
0)
#5970000
b1101 @
b11 8
1)
#5980000
0)
#5990000
b100 8
b1110 @
1)
#6000000
0)
#6010000
1%
b1111 @
b101 8
1)
#6020000
0)
#6030000
0%
b110 8
b111 ?
b0 @
1)
#6040000
0)
#6050000
b1 @
0!
b111 8
1)
#6060000
0)
#6070000
b1000 8
b10 @
1)
#6080000
0)
#6090000
b11 @
b1001 8
1)
#6100000
0)
#6110000
b1010 8
b100 @
1)
#6120000
0)
#6130000
b101 @
b1011 8
1)
#6140000
0)
#6150000
b1100 8
b110 @
1)
#6160000
0)
#6170000
b111 @
b1101 8
1)
#6180000
0)
#6190000
b1110 8
b1000 @
1)
#6200000
0)
#6210000
b1001 @
b1111 8
1)
#6220000
0)
#6230000
b11 5
b0 8
b1011010 7
b1010 @
1)
#6240000
0)
#6250000
b1011 @
b1 8
1)
#6260000
0)
#6270000
b10 8
b1100 @
1)
#6280000
0)
#6290000
b1101 @
b11 8
1)
#6300000
0)
#6310000
b100 8
b1110 @
1)
#6320000
0)
#6330000
1%
b1111 @
b101 8
1)
#6340000
0)
#6350000
0%
b110 8
b11 A
b0 @
1)
#6360000
0)
#6370000
b1 @
1!
b111 8
1)
#6380000
0)
#6390000
b1000 8
b10 @
1)
#6400000
0)
#6410000
b11 @
b1001 8
1)
#6420000
0)
#6430000
b1010 8
b100 @
1)
#6440000
0)
#6450000
b101 @
b1011 8
1)
#6460000
0)
#6470000
b1100 8
b110 @
1)
#6480000
0)
#6490000
b111 @
b1101 8
1)
#6500000
0)
#6510000
b1110 8
b1000 @
1)
#6520000
0)
#6530000
b1001 @
b1111 8
1)
#6540000
0)
#6550000
b1010101 C
b0 5
1#
b1011010 $
b1011010 6
b1010 @
1)
#6560000
0)
#6570000
b1011 @
0#
1)
#6580000
0)
#6590000
b1100 @
1)
#6600000
0)
#6610000
b1101 @
1)
#6620000
0)
#6630000
b1110 @
1)
#6640000
0)
#6650000
1%
b1111 @
1)
#6660000
0)
#6670000
0"
0%
b0 A
b0 @
1)
#6680000
0)
#6690000
b1 @
1,
b1010101 +
b1010101 9
1)
#6700000
0)
#6710000
1"
0,
b1 A
b0 ?
b1010101 B
b0 @
1)
#6720000
0)
#6730000
b1 @
0!
1)
#6740000
0)
#6750000
b1 5
b0 8
b10 @
1)
#6760000
0)
#6770000
b11 @
b1 8
1)
#6780000
0)
#6790000
b10 8
b100 @
1)
#6800000
0)
#6810000
b101 @
b11 8
1)
#6820000
0)
#6830000
b100 8
b110 @
1)
#6840000
0)
#6850000
b111 @
b101 8
1)
#6860000
0)
#6870000
b110 8
b1000 @
1)
#6880000
0)
#6890000
b1001 @
b111 8
1)
#6900000
0)
#6910000
b10 5
b0 3
b0 8
b1010 @
1)
#6920000
0)
#6930000
b1011 @
b1 8
1)
#6940000
0)
#6950000
b10 8
b1100 @
1)
#6960000
0)
#6970000
b1101 @
b11 8
1)
#6980000
0)
#6990000
b100 8
b1110 @
1)
#7000000
0)
#7010000
1%
b1111 @
b101 8
1)
#7020000
0)
#7030000
0%
b110 8
b10 A
b0 @
1)
#7040000
0)
#7050000
b1 @
1!
b111 8
1)
